yarn_kernel_provider/__init__.py
yarn_kernel_provider/_version.py
yarn_kernel_provider/kernelspecapp.py
yarn_kernel_provider/provider.py
yarn_kernel_provider/yarn.py
yarn_kernel_provider/kernelspecs/yarnkp_dask_python/yarnkp_kernel.json
yarn_kernel_provider/kernelspecs/yarnkp_dask_python/bin/run.sh
yarn_kernel_provider/kernelspecs/yarnkp_spark_python/yarnkp_kernel.json
yarn_kernel_provider/kernelspecs/yarnkp_spark_python/bin/run.sh
yarn_kernel_provider/kernelspecs/yarnkp_spark_r/yarnkp_kernel.json
yarn_kernel_provider/kernelspecs/yarnkp_spark_r/bin/run.sh
yarn_kernel_provider/kernelspecs/yarnkp_spark_scala/yarnkp_kernel.json
yarn_kernel_provider/kernelspecs/yarnkp_spark_scala/bin/run.sh
yarn_kernel_provider/tests/test_kernelspec_app.py
yarn_kernel_provider-0.2.0.dist-info/LICENSE
yarn_kernel_provider-0.2.0.dist-info/METADATA
yarn_kernel_provider-0.2.0.dist-info/WHEEL
yarn_kernel_provider-0.2.0.dist-info/entry_points.txt
yarn_kernel_provider-0.2.0.dist-info/top_level.txt
yarn_kernel_provider-0.2.0.dist-info/RECORD
