Metadata-Version: 2.1
Name: yarn-kernel-provider
Version: 0.2.0
Summary: Provides support for launching Jupyter kernels within a YARN cluster
Home-page: https://jupyter.org
Author: Jupyter Development Team
Author-email: jupyter@googlegroups.com
License: BSD
Platform: UNKNOWN
Classifier: Intended Audience :: Developers
Classifier: Intended Audience :: System Administrators
Classifier: Intended Audience :: Science/Research
Classifier: License :: OSI Approved :: BSD License
Classifier: Programming Language :: Python
Classifier: Programming Language :: Python :: 3
Requires-Python: >=3.5
Requires-Dist: remote-kernel-provider (>=0.3.0)
Requires-Dist: jupyter-kernel-mgmt (>=0.5.1)
Requires-Dist: entrypoints
Requires-Dist: requests
Requires-Dist: yarn-api-client (>=1.0)
Provides-Extra: kerberos
Requires-Dist: requests-kerberos ; extra == 'kerberos'
